{
  "effect_push": {
    "sounds": [
      {
        "name": "ars_zero:effect_push",
        "stream": false
      }
    ]
  },
  "effect_anchor": {
    "sounds": [
      {
        "name": "ars_zero:effect_anchor",
        "stream": false
      }
    ]
  },
  "lightning_voxel_hit": {
    "sounds": [
      {
        "name": "ars_zero:lightning_voxel_hit",
        "stream": false
      }
    ]
  },
  "explosion_charge": {
    "sounds": [
      {
        "name": "ars_zero:explosion_charge",
        "stream": false
      }
    ]
  },
  "explosion_idle": {
    "sounds": [
      {
        "name": "ars_zero:explosion_idle",
        "stream": false
      }
    ]
  },
  "explosion_activate": {
    "sounds": [
      {
        "name": "ars_zero:explosion_activate",
        "stream": false
      }
    ]
  },
  "explosion_priming": {
    "sounds": [
      {
        "name": "ars_zero:explosion_priming",
        "stream": false
      }
    ]
  },
  "explosion_distant": {
    "sounds": [
      {
        "name": "ars_zero:explosion_distant",
        "stream": false
      }
    ]
  },
  "splash_fast": {
    "sounds": [
      {
        "name": "ars_zero:splash_fast_1",
        "stream": false
      },
      {
        "name": "ars_zero:splash_fast_2",
        "stream": false
      }
    ]
  }
}
