{
  "type": "minecraft:crafting_shapeless",
  "category": "misc",
  "ingredients": [
    {
      "item": "ars_zero:novice_spell_staff"
    },
    {
      "tag": "c:obsidians"
    },
    {
      "tag": "c:gems/diamond"
    },
    {
      "tag": "c:gems/diamond"
    },
    {
      "tag": "c:gems/diamond"
    },
    {
      "item": "minecraft:quartz_block"
    },
    {
      "item": "minecraft:quartz_block"
    },
    {
      "tag": "c:rods/blaze"
    },
    {
      "tag": "c:rods/blaze"
    }
  ],
  "result": {
    "count": 1,
    "id": "ars_zero:mage_spell_staff"
  }
}